awcon/__init__.py
awcon-1.1.0.dist-info/LICENSE
awcon-1.1.0.dist-info/METADATA
awcon-1.1.0.dist-info/WHEEL
awcon-1.1.0.dist-info/top_level.txt
awcon-1.1.0.dist-info/RECORD
