Metadata-Version: 2.1
Name: awcon
Version: 1.1.0
Summary: AnyWord connector
Home-page: https://wispace.ru/
Author: WiSpace
Author-email: wiforumit@gmail.com
License: UNKNOWN
Platform: UNKNOWN
Classifier: Programming Language :: Python :: 3.8
Requires-Python: >=3.6
License-File: LICENSE
